dotzen/__init__.py
dotzen/cli.py
dotzen/dotzen.py
dotzen/encryption.py
dotzen-1.1.0.dist-info/licenses/LICENSE
dotzen-1.1.0.dist-info/METADATA
dotzen-1.1.0.dist-info/WHEEL
dotzen-1.1.0.dist-info/entry_points.txt
dotzen-1.1.0.dist-info/top_level.txt
dotzen-1.1.0.dist-info/RECORD
