Metadata-Version: 2.4
Name: dotzen
Version: 1.1.0
Summary: Peaceful, type-safe Python configuration with strict separation from code
Home-page: https://github.com/carrington-dev/dotzen
Author: Carrington Muleya
Author-email: Carrington Muleya <carrington.muleya@outlook.com>
License: MIT
Project-URL: Homepage, https://github.com/carrington-dev/dotzen
Project-URL: Documentation, https://dotzen.readthedocs.io
Project-URL: Repository, https://github.com/carrington-dev/dotzen
Project-URL: Bug Tracker, https://github.com/carrington-dev/dotzen/issues
Project-URL: Changelog, https://github.com/carrington-dev/dotzen/blob/main/CHANGELOG.md
Keywords: configuration,config,settings,environment,env,dotenv,secrets,cloud,aws,gcp,azure,type-safe,validation
Classifier: Development Status :: 4 - Beta
Classifier: Intended Audience :: Developers
Classifier: License :: OSI Approved :: MIT License
Classifier: Programming Language :: Python :: 3
Classifier: Programming Language :: Python :: 3.8
Classifier: Programming Language :: Python :: 3.9
Classifier: Programming Language :: Python :: 3.10
Classifier: Programming Language :: Python :: 3.11
Classifier: Programming Language :: Python :: 3.12
Classifier: Programming Language :: Python :: 3.13
Classifier: Typing :: Typed
Requires-Python: >=3.8
License-File: LICENSE
Provides-Extra: aws
Requires-Dist: boto3>=1.26.0; extra == "aws"
Requires-Dist: botocore>=1.29.0; extra == "aws"
Provides-Extra: gcp
Requires-Dist: google-cloud-secret-manager>=2.16.0; extra == "gcp"
Provides-Extra: azure
Requires-Dist: azure-keyvault-secrets>=4.7.0; extra == "azure"
Requires-Dist: azure-identity>=1.12.0; extra == "azure"
Provides-Extra: vault
Requires-Dist: hvac>=1.2.0; extra == "vault"
Provides-Extra: yaml
Requires-Dist: PyYAML>=6.0; extra == "yaml"
Provides-Extra: toml
Requires-Dist: tomli>=2.0.0; python_version < "3.11" and extra == "toml"
Provides-Extra: json5
Requires-Dist: json5>=0.9.0; extra == "json5"
Provides-Extra: cloud
Requires-Dist: boto3>=1.26.0; extra == "cloud"
Requires-Dist: google-cloud-secret-manager>=2.16.0; extra == "cloud"
Requires-Dist: azure-keyvault-secrets>=4.7.0; extra == "cloud"
Requires-Dist: azure-identity>=1.12.0; extra == "cloud"
Requires-Dist: hvac>=1.2.0; extra == "cloud"
Provides-Extra: formats
Requires-Dist: PyYAML>=6.0; extra == "formats"
Requires-Dist: tomli>=2.0.0; python_version < "3.11" and extra == "formats"
Requires-Dist: json5>=0.9.0; extra == "formats"
Provides-Extra: dev
Requires-Dist: pytest>=7.0.0; extra == "dev"
Requires-Dist: pytest-cov>=4.0.0; extra == "dev"
Requires-Dist: pytest-asyncio>=0.21.0; extra == "dev"
Requires-Dist: pytest-mock>=3.10.0; extra == "dev"
Requires-Dist: black>=23.0.0; extra == "dev"
Requires-Dist: ruff>=0.1.0; extra == "dev"
Requires-Dist: mypy>=1.0.0; extra == "dev"
Requires-Dist: pre-commit>=3.0.0; extra == "dev"
Requires-Dist: tox>=4.0.0; extra == "dev"
Provides-Extra: docs
Requires-Dist: sphinx>=6.0.0; extra == "docs"
Requires-Dist: sphinx-rtd-theme>=1.2.0; extra == "docs"
Requires-Dist: sphinx-autodoc-typehints>=1.22.0; extra == "docs"
Requires-Dist: myst-parser>=1.0.0; extra == "docs"
Provides-Extra: test
Requires-Dist: pytest>=7.0.0; extra == "test"
Requires-Dist: pytest-cov>=4.0.0; extra == "test"
Requires-Dist: pytest-asyncio>=0.21.0; extra == "test"
Requires-Dist: pytest-mock>=3.10.0; extra == "test"
Requires-Dist: moto[secretsmanager]>=4.0.0; extra == "test"
Requires-Dist: responses>=0.23.0; extra == "test"
Provides-Extra: all
Requires-Dist: boto3>=1.26.0; extra == "all"
Requires-Dist: google-cloud-secret-manager>=2.16.0; extra == "all"
Requires-Dist: azure-keyvault-secrets>=4.7.0; extra == "all"
Requires-Dist: azure-identity>=1.12.0; extra == "all"
Requires-Dist: hvac>=1.2.0; extra == "all"
Requires-Dist: PyYAML>=6.0; extra == "all"
Requires-Dist: tomli>=2.0.0; python_version < "3.11" and extra == "all"
Requires-Dist: json5>=0.9.0; extra == "all"
Dynamic: author
Dynamic: home-page
Dynamic: license-file
Dynamic: requires-python
